pointcloudqueries.cp39-win_amd64.pyd
pointcloudqueries-0.0.1.dist-info/METADATA
pointcloudqueries-0.0.1.dist-info/WHEEL
pointcloudqueries-0.0.1.dist-info/top_level.txt
pointcloudqueries-0.0.1.dist-info/RECORD
